mores_encryption/__init__.py
mores_encryption/encryption.py
mores_encryption-0.1.5.dist-info/licenses/LICENSE
mores_encryption-0.1.5.dist-info/METADATA
mores_encryption-0.1.5.dist-info/WHEEL
mores_encryption-0.1.5.dist-info/top_level.txt
mores_encryption-0.1.5.dist-info/RECORD
