Metadata-Version: 2.4
Name: mores-encryption
Version: 0.1.5
Summary: Lightweight, production-grade AES/Fernet encryption & deterministic hashing library.
Author-email: Hemant Kumar <hemant.kumardeveloper@gmail.com>
License: MIT License
Project-URL: Homepage, https://github.com/HATAKEkakshi/mores-encryption.git
Project-URL: Documentation, https://github.com/HATAKEkakshi/mores-encryption.git
Project-URL: Source, https://github.com/HATAKEkakshi/mores-encryption.git
Project-URL: Issues, https://github.com/HATAKEkakshi/mores-encryption/issues
Requires-Python: >=3.8
License-File: LICENSE
Requires-Dist: cryptography>=42.0.0
Dynamic: license-file
